CHANGELOG.txt
LICENSE.txt
MANIFEST.in
README.txt
setup.py
django_googleanalytics.egg-info/PKG-INFO
django_googleanalytics.egg-info/SOURCES.txt
django_googleanalytics.egg-info/dependency_links.txt
django_googleanalytics.egg-info/not-zip-safe
django_googleanalytics.egg-info/top_level.txt
google_analytics/__init__.py
google_analytics/templates/google_analytics/tracking_code.html
google_analytics/templatetags/__init__.py
google_analytics/templatetags/googleanalytics_tags.py