Metadata-Version: 1.0
Name: django-googleanalytics
Version: 1.0
Summary: Google Analytics templatetag for Django
Home-page: http://code.google.com/p/django-googleanalytics/
Author: Gonzalo Saavedra
Author-email: gonzalosaavedra@gmail.com
License: BSD
Platform: UNKNOWN
Classifier: Development Status :: 3 - Alpha
Classifier: Environment :: Web Environment
Classifier: Framework :: Django
Classifier: Intended Audience :: Developers
Classifier: License :: OSI Approved :: BSD License
Classifier: Operating System :: OS Independent
Classifier: Programming Language :: Python
Classifier: Framework :: Django
